Metadata-Version: 2.1
Name: odoo14-addon-sale_coupon_multi_gift
Version: 14.0.1.0.1.dev6
Summary: Allows to configure multiple gift rewards per promotion
Home-page: https://github.com/OCA/sale-promotion
Author: Tecnativa, Odoo Community Association (OCA)
Author-email: support@odoo-community.org
License: AGPL-3
Classifier: Programming Language :: Python
Classifier: Framework :: Odoo
Classifier: Framework :: Odoo :: 14.0
Classifier: License :: OSI Approved :: GNU Affero General Public License v3
Classifier: Development Status :: 4 - Beta
Requires-Python: >=3.6
Requires-Dist: odoo14-addon-sale-coupon-order-line-link
Requires-Dist: odoo<14.1dev,>=14.0a
